flipt_pb2.py
flipt_pb2_grpc.py
flipt_grpc_python-0.2.0.dist-info/LICENSE
flipt_grpc_python-0.2.0.dist-info/WHEEL
flipt_grpc_python-0.2.0.dist-info/METADATA
flipt_grpc_python-0.2.0.dist-info/RECORD
