Metadata-Version: 2.1
Name: flipt-grpc-python
Version: 0.2.0
Summary: 
License: Apache-2.0
Author: David Cramer
Author-email: dcramer@gmail.com
Requires-Python: >=2.7, !=3.0.*, !=3.1.*, !=3.2.*, !=3.3.*, !=3.4.*
Classifier: License :: OSI Approved :: Apache Software License
Classifier: Programming Language :: Python :: 2
Classifier: Programming Language :: Python :: 2.7
Classifier: Programming Language :: Python :: 3
Classifier: Programming Language :: Python :: 3.5
Classifier: Programming Language :: Python :: 3.6
Classifier: Programming Language :: Python :: 3.7
Classifier: Programming Language :: Python :: 3.8
Classifier: Programming Language :: Python :: 3.9
Requires-Dist: grpcio (>=1.28.1,<2.0.0)
Requires-Dist: grpcio-tools (>=1.28.1,<2.0.0)
Requires-Dist: protoc-gen-swagger (>=0.1.0,<0.2.0)
